gym3/__init__.py
gym3/asynchronous.py
gym3/asynchronous_test.py
gym3/concat.py
gym3/concat_test.py
gym3/env.py
gym3/extract_dict_ob.py
gym3/interactive.py
gym3/interop.py
gym3/interop_test.py
gym3/libenv.h
gym3/libenv.py
gym3/libenv_test.py
gym3/subproc.py
gym3/subproc_test.py
gym3/testing.py
gym3/testing_test.py
gym3/trajectory_recorder.py
gym3/trajectory_recorder_test.py
gym3/types.py
gym3/types_np.py
gym3/types_th.py
gym3/util.py
gym3/video_recorder.py
gym3/video_recorder_test.py
gym3/viewer.py
gym3/wrapper.py
gym3/wrappers.py
gym3/internal/__init__.py
gym3/internal/font.bin
gym3/internal/misc.py
gym3/internal/renderer.py
gym3/internal/test_with_mpi.py
gym3/scripts/__init__.py
gym3/scripts/random_agent.py
pufferai_gym3/__init__.py
pufferai_gym3/asynchronous.py
pufferai_gym3/asynchronous_test.py
pufferai_gym3/concat.py
pufferai_gym3/concat_test.py
pufferai_gym3/env.py
pufferai_gym3/extract_dict_ob.py
pufferai_gym3/interactive.py
pufferai_gym3/interop.py
pufferai_gym3/interop_test.py
pufferai_gym3/libenv.py
pufferai_gym3/libenv_test.py
pufferai_gym3/subproc.py
pufferai_gym3/subproc_test.py
pufferai_gym3/testing.py
pufferai_gym3/testing_test.py
pufferai_gym3/trajectory_recorder.py
pufferai_gym3/trajectory_recorder_test.py
pufferai_gym3/types.py
pufferai_gym3/types_np.py
pufferai_gym3/types_th.py
pufferai_gym3/util.py
pufferai_gym3/video_recorder.py
pufferai_gym3/video_recorder_test.py
pufferai_gym3/viewer.py
pufferai_gym3/wrapper.py
pufferai_gym3/wrappers.py
pufferai_gym3/internal/__init__.py
pufferai_gym3/internal/misc.py
pufferai_gym3/internal/renderer.py
pufferai_gym3/internal/test_with_mpi.py
pufferai_gym3/scripts/__init__.py
pufferai_gym3/scripts/random_agent.py
pufferai_gym3-0.3.3.2.dist-info/LICENSE
pufferai_gym3-0.3.3.2.dist-info/LICENSES.md
pufferai_gym3-0.3.3.2.dist-info/METADATA
pufferai_gym3-0.3.3.2.dist-info/WHEEL
pufferai_gym3-0.3.3.2.dist-info/top_level.txt
pufferai_gym3-0.3.3.2.dist-info/RECORD
