Metadata-Version: 2.1
Name: pufferai_gym3
Version: 0.3.3.2
Summary: Vectorized Reinforcement Learning Environment Interface
Home-page: https://github.com/pufferai/gym3
Author: OpenAI
Requires-Python: >=3.6.0
License-File: LICENSE
License-File: LICENSES.md
Requires-Dist: numpy <2.0.0,>=1.11.0
Requires-Dist: cffi <2.0.0,>=1.13.0
Requires-Dist: imageio <3.0.0,>=2.6.0
Requires-Dist: imageio-ffmpeg <0.4.0,>=0.3.0
Requires-Dist: glfw ==2.7
Requires-Dist: moderngl <6.0.0,>=5.5.4
Provides-Extra: test
Requires-Dist: pytest ==5.2.1 ; extra == 'test'
Requires-Dist: pytest-benchmark ==3.2.2 ; extra == 'test'
Requires-Dist: gym-retro ==0.8.0 ; extra == 'test'
Requires-Dist: gym ==0.17.2 ; extra == 'test'
Requires-Dist: tensorflow ==1.15.0 ; extra == 'test'
Requires-Dist: mpi4py ==3.0.3 ; extra == 'test'
